setup.py
AsyncIRC.egg-info/PKG-INFO
AsyncIRC.egg-info/SOURCES.txt
AsyncIRC.egg-info/dependency_links.txt
AsyncIRC.egg-info/top_level.txt
asyncirc/__init__.py
asyncirc/ircbot.py
asyncirc/ircclient.py