Metadata-Version: 1.1
Name: AsyncIRC
Version: 0.0.2
Summary: Dependancy-free Asynchronous IRC Library
Home-page: https://github.com/kageurufu/asyncirc
Author: Franklyn Tackitt
Author-email: franklyn@tackitt.net
License: UNKNOWN
Platform: UNKNOWN
Classifier: Topic :: System :: Networking
